redisbench_admin/__init__.py
redisbench_admin/cli.py
redisbench_admin/commands/__init__.py
redisbench_admin/commands/commands.json.py
redisbench_admin/compare/__init__.py
redisbench_admin/compare/args.py
redisbench_admin/compare/compare.py
redisbench_admin/deploy/__init__.py
redisbench_admin/deploy/args.py
redisbench_admin/deploy/deploy.py
redisbench_admin/environments/__init__.py
redisbench_admin/environments/oss_cluster.py
redisbench_admin/environments/oss_standalone.py
redisbench_admin/export/__init__.py
redisbench_admin/export/args.py
redisbench_admin/export/common/__init__.py
redisbench_admin/export/common/common.py
redisbench_admin/export/export.py
redisbench_admin/export/google_benchmark/__init__.py
redisbench_admin/export/google_benchmark/google_benchmark_json_format.py
redisbench_admin/export/memtier_benchmark/__init__.py
redisbench_admin/export/memtier_benchmark/memtier_benchmark_json_format.py
redisbench_admin/export/pyperf/__init__.py
redisbench_admin/export/pyperf/pyperf_json_format.py
redisbench_admin/export/redis_benchmark/__init__.py
redisbench_admin/export/redis_benchmark/metrics_definition.py
redisbench_admin/export/redis_benchmark/redis_benchmark_csv_format.py
redisbench_admin/extract/__init__.py
redisbench_admin/extract/args.py
redisbench_admin/extract/extract.py
redisbench_admin/grafana_api/__init__.py
redisbench_admin/grafana_api/app.py
redisbench_admin/grafana_api/args.py
redisbench_admin/grafana_api/grafana_api.py
redisbench_admin/profilers/__init__.py
redisbench_admin/profilers/daemon.py
redisbench_admin/profilers/flamegraph.pl
redisbench_admin/profilers/perf.py
redisbench_admin/profilers/perf_daemon_caller.py
redisbench_admin/profilers/pprof.py
redisbench_admin/profilers/profilers.py
redisbench_admin/profilers/profilers_local.py
redisbench_admin/profilers/profilers_schema.py
redisbench_admin/profilers/stackcollapse-perf.pl
redisbench_admin/profilers/vtune.py
redisbench_admin/run/__init__.py
redisbench_admin-0.11.69.dist-info/METADATA
redisbench_admin-0.11.69.dist-info/WHEEL
redisbench_admin-0.11.69.dist-info/entry_points.txt
redisbench_admin-0.11.69.dist-info/licenses/LICENSE
redisbench_admin-0.11.69.dist-info/RECORD
