Metadata-Version: 2.4
Name: redisbench-admin
Version: 0.11.69
Summary: Redis benchmark run helper. A wrapper around Redis and Redis Modules benchmark tools ( ftsb_redisearch, memtier_benchmark, redis-benchmark, aibench, etc... ).
License-File: LICENSE
Author: filipecosta90
Author-email: filipecosta.90@gmail.com
Requires-Python: >=3.10.0,<4.0.0
Classifier: Programming Language :: Python :: 3
Classifier: Programming Language :: Python :: 3.10
Classifier: Programming Language :: Python :: 3.11
Classifier: Programming Language :: Python :: 3.12
Classifier: Programming Language :: Python :: 3.13
Classifier: Programming Language :: Python :: 3.14
Requires-Dist: Flask (>=2.0.1,<3.0.0)
Requires-Dist: Flask-HTTPAuth (>=4.4.0,<5.0.0)
Requires-Dist: GitPython (>=3.1.12,<4.0.0)
Requires-Dist: Jinja2 (>=3.0.3,<4.0.0)
Requires-Dist: PyYAML (>=6.0.1,<7.0.0)
Requires-Dist: boto3 (>=1.13.24,<2.0.0)
Requires-Dist: certifi (>=2021.10.8,<2025.0.0)
Requires-Dist: daemonize (>=2.5.0,<3.0.0)
Requires-Dist: flask-restx (>=0.5.1,<0.6.0)
Requires-Dist: humanize (>=2.4.0,<3.0.0)
Requires-Dist: jsonpath_ng (>=1.5.2,<2.0.0)
Requires-Dist: matplotlib (>=3.9.0,<4.0.0)
Requires-Dist: numpy (>=2.0.0,<3.0.0)
Requires-Dist: pandas (>=2.1.2,<3.0.0)
Requires-Dist: paramiko (>=2.7.2,<4.0.0)
Requires-Dist: psutil (>=5.6.6,<6.0.0)
Requires-Dist: pyWorkFlow (>=0.0.2,<0.0.3)
Requires-Dist: py_cpuinfo (>=5.0.0,<6.0.0)
Requires-Dist: pygithub (>=1.57,<2.0)
Requires-Dist: pysftp (>=0.2.9,<0.3.0)
Requires-Dist: pytablewriter[html] (>=0.64.1,<0.65.0)
Requires-Dist: python_terraform (>=0.10.1,<0.11.0)
Requires-Dist: redis (>=4.2.2,<5.0.0)
Requires-Dist: requests (>=2.32.3,<3.0.0)
Requires-Dist: slack-bolt (>=1.13.0,<2.0.0)
Requires-Dist: slack-sdk (>=3.15.2,<4.0.0)
Requires-Dist: sshtunnel (>=0.4.0,<0.5.0)
Requires-Dist: toml (>=0.10.1,<0.11.0)
Requires-Dist: tqdm (>=4.46.1,<5.0.0)
Requires-Dist: watchdog (>=2.1.6,<3.0.0)
Requires-Dist: wget (>=3.2,<4.0)
